pyndakaas/__init__.py
pyndakaas/front_matter_parsers.py
pyndakaas/handler.py
pyndakaas/processing.py
pyndakaas-0.2.1.dist-info/licenses/LICENSE
pyndakaas-0.2.1.dist-info/METADATA
pyndakaas-0.2.1.dist-info/WHEEL
pyndakaas-0.2.1.dist-info/top_level.txt
pyndakaas-0.2.1.dist-info/RECORD
