Metadata-Version: 2.4
Name: pyndakaas
Version: 0.2.1
Summary: An extensible static site generator.
Author-email: Ruben van Nieuwpoort <ruben@vannieuwpoort.dev>
License-Expression: MIT
Project-URL: homepage, https://github.com/rubenvannieuwpoort/pyndakaas
Classifier: Development Status :: 3 - Alpha
Classifier: Programming Language :: Python :: 3
Requires-Python: >=3
License-File: LICENSE
Requires-Dist: Jinja2>=3
Provides-Extra: dev
Requires-Dist: types-Jinja2; extra == "dev"
Requires-Dist: flake8>=7.3; extra == "dev"
Requires-Dist: mypy>=1.18; extra == "dev"
Dynamic: license-file
